pickn/__init__.py
pickn-1.0.0.dist-info/METADATA
pickn-1.0.0.dist-info/WHEEL
pickn-1.0.0.dist-info/top_level.txt
pickn-1.0.0.dist-info/RECORD
